pycivitai/__init__.py
pycivitai/__main__.py
pycivitai/dispatch.py
pycivitai/entry.py
pycivitai/client/__init__.py
pycivitai/client/http.py
pycivitai/client/resource.py
pycivitai/config/__init__.py
pycivitai/config/meta.py
pycivitai/manager/__init__.py
pycivitai/manager/base.py
pycivitai/manager/dispatch.py
pycivitai/manager/model.py
pycivitai/manager/version.py
pycivitai/utils/__init__.py
pycivitai/utils/cli.py
pycivitai/utils/download.py
pycivitai-0.2.0.dist-info/LICENSE
pycivitai-0.2.0.dist-info/METADATA
pycivitai-0.2.0.dist-info/WHEEL
pycivitai-0.2.0.dist-info/entry_points.txt
pycivitai-0.2.0.dist-info/top_level.txt
pycivitai-0.2.0.dist-info/RECORD
